{"name":"Pilates","slug":"pilates","tags":[{"tag":"active","overlap":0.7},{"tag":"indoor","overlap":0.9},{"tag":"physical","overlap":0.7},{"tag":"individual","overlap":0.9},{"tag":"focused","overlap":0.8},{"tag":"low-impact","overlap":0.9},{"tag":"balance","overlap":0.8},{"tag":"strength","overlap":0.7}],"description":"A system of exercises using special apparatus, designed to improve physical strength, flexibility, posture, and enhance mental awareness.","resources":[{"name":"Pilates Foundation","url":"https://www.pilatesfoundation.com/"},{"name":"r/pilates","url":"https://www.reddit.com/r/pilates/"},{"name":"Blogilates","url":"https://www.blogilates.com/"},{"name":"Pilates Anytime","url":"https://www.pilatesanytime.com/"},{"name":"Move With Nicole (YouTube)","url":"https://www.youtube.com/user/nicolepearceyoga"}]}