{"name":"Sketching","slug":"sketching","tags":[{"tag":"indoor","overlap":0.9},{"tag":"outdoor","overlap":0.7},{"tag":"art","overlap":0.9},{"tag":"creative","overlap":0.9},{"tag":"visual","overlap":0.9},{"tag":"fine-motor-skills","overlap":0.8},{"tag":"aesthetic","overlap":0.9}],"description":"Practice drawing quickly and spontaneously, often as preparation for more detailed artwork or to capture ideas.","resources":[{"name":"Urban Sketchers","url":"https://urbansketchers.org/"},{"name":"Reddit: r/sketchdaily","url":"https://www.reddit.com/r/sketchdaily/"},{"name":"Draw a Box","url":"https://drawabox.com/"},{"name":"Love Life Drawing","url":"https://www.lovelifedrawing.com/"},{"name":"Alphonso Dunn (YouTube)","url":"https://www.youtube.com/user/alphonsodunnart"}]}