{"name":"Sketching (Figure Drawing)","slug":"sketching-figure-drawing","tags":[{"tag":"art","overlap":0.9},{"tag":"visual","overlap":0.9},{"tag":"creative","overlap":0.9},{"tag":"skill-based","overlap":0.8},{"tag":"fine-motor-skills","overlap":0.8},{"tag":"indoor","overlap":0.9},{"tag":"at-home","overlap":0.9},{"tag":"focused","overlap":0.8}],"description":"Drawing the human form in various poses and styles.","resources":[{"name":"New Masters Academy","url":"https://nma.art/"},{"name":"YouTube: Figure Drawing Tutorials","url":"https://www.youtube.com/results?search_query=figure+drawing+tutorials"},{"name":"Reddit: r/figuredrawing","url":"https://www.reddit.com/r/figuredrawing/"},{"name":"Proko","url":"https://proko.com/"},{"name":"Local Life Drawing Sessions Search","url":"https://www.google.com/search?q=local+life+drawing+sessions"}]}