{"name":"Whittling (Wood Carving)","slug":"whittling-wood-carving","tags":[{"tag":"crafts","overlap":0.9},{"tag":"tangible-creation","overlap":0.9},{"tag":"art","overlap":0.8},{"tag":"natural-materials","overlap":0.9},{"tag":"hand-tools","overlap":0.8},{"tag":"fine-motor-skills","overlap":0.8},{"tag":"skill-based","overlap":0.8},{"tag":"relaxing","overlap":0.7}],"description":"Carving wood using a knife to create shapes and designs.","resources":[{"name":"Wood Carving Illustrated","url":"https://www.woodcarvingillustrated.com/"},{"name":"YouTube: Whittling Tutorials","url":"https://www.youtube.com/results?search_query=whittling+tutorials"},{"name":"Reddit: r/woodcarving","url":"https://www.reddit.com/r/woodcarving/"},{"name":"Pinewood Forge","url":"https://www.pinewoodforge.com/"},{"name":"The Carving Shop","url":"https://www.thecarvingshop.com/"}]}