{"name":"Windsurfing","slug":"windsurfing","tags":[{"tag":"sports","overlap":0.9},{"tag":"active","overlap":0.9},{"tag":"physical","overlap":0.9},{"tag":"water-based","overlap":0.9},{"tag":"outdoor","overlap":0.9},{"tag":"skill-based","overlap":0.9},{"tag":"weather-dependent","overlap":0.9},{"tag":"requires-equipment","overlap":0.8}],"description":"A surface water sport that uses wind acting on a sail to propel the rider across the water on a board.","resources":[{"name":"US Windsurfing","url":"https://uswindsurfing.org/"},{"name":"YouTube: Windsurfing Techniques and Races","url":"https://www.youtube.com/user/FilmRiot0"},{"name":"Reddit: r/windsurfing","url":"https://www.reddit.com/r/windsurfing/"},{"name":"Windsurf Magazine","url":"https://www.windsurf.co.uk/"},{"name":"Find a Local Windsurfing School","url":"https://www.google.com/search?q=local+windsurfing+school"}]}